setup.py
nanodegree_excercise5_distributions/Binomialdistribution.py
nanodegree_excercise5_distributions/Gaussiandistribution.py
nanodegree_excercise5_distributions/Generaldistribution.py
nanodegree_excercise5_distributions/__init__.py
nanodegree_excercise5_distributions.egg-info/PKG-INFO
nanodegree_excercise5_distributions.egg-info/SOURCES.txt
nanodegree_excercise5_distributions.egg-info/dependency_links.txt
nanodegree_excercise5_distributions.egg-info/not-zip-safe
nanodegree_excercise5_distributions.egg-info/top_level.txt